annofabcli/__init__.py
annofabcli/__main__.py
annofabcli/__version__.py
annofabcli/annotation/__init__.py
annofabcli/annotation/annotation_query.py
annofabcli/annotation/change_annotation_attributes.py
annofabcli/annotation/change_annotation_properties.py
annofabcli/annotation/copy_annotation.py
annofabcli/annotation/delete_annotation.py
annofabcli/annotation/download_annotation_zip.py
annofabcli/annotation/dump_annotation.py
annofabcli/annotation/import_annotation.py
annofabcli/annotation/list_annotation.py
annofabcli/annotation/list_annotation_count.py
annofabcli/annotation/merge_segmentation.py
annofabcli/annotation/remove_segmentation_overlap.py
annofabcli/annotation/restore_annotation.py
annofabcli/annotation/subcommand_annotation.py
annofabcli/annotation_specs/__init__.py
annofabcli/annotation_specs/add_attribute_restriction.py
annofabcli/annotation_specs/attribute_restriction.py
annofabcli/annotation_specs/export_annotation_specs.py
annofabcli/annotation_specs/get_annotation_specs_with_attribute_id_replaced.py
annofabcli/annotation_specs/get_annotation_specs_with_choice_id_replaced.py
annofabcli/annotation_specs/get_annotation_specs_with_label_id_replaced.py
annofabcli/annotation_specs/list_annotation_specs_attribute.py
annofabcli/annotation_specs/list_annotation_specs_choice.py
annofabcli/annotation_specs/list_annotation_specs_history.py
annofabcli/annotation_specs/list_annotation_specs_label.py
annofabcli/annotation_specs/list_annotation_specs_label_attribute.py
annofabcli/annotation_specs/list_attribute_restriction.py
annofabcli/annotation_specs/list_label_color.py
annofabcli/annotation_specs/put_label_color.py
annofabcli/annotation_specs/subcommand_annotation_specs.py
annofabcli/comment/__init__.py
annofabcli/comment/delete_comment.py
annofabcli/comment/download_comment_json.py
annofabcli/comment/list_all_comment.py
annofabcli/comment/list_comment.py
annofabcli/comment/put_comment.py
annofabcli/comment/put_comment_simply.py
annofabcli-100.3.dist-info/LICENSE
annofabcli-100.3.dist-info/METADATA
annofabcli-100.3.dist-info/WHEEL
annofabcli-100.3.dist-info/entry_points.txt
annofabcli-100.3.dist-info/RECORD
