Metadata-Version: 2.1
Name: annofabcli
Version: 100.3
Summary: Utility Command Line Interface for AnnoFab
Home-page: https://github.com/kurusugawa-computer/annofab-cli
License: MIT
Keywords: annofab,cli
Author: yuji38kwmt
Requires-Python: >=3.9,<4.0
Classifier: Development Status :: 4 - Beta
Classifier: Environment :: Console
Classifier: Intended Audience :: Developers
Classifier: License :: OSI Approved :: MIT License
Classifier: Operating System :: OS Independent
Classifier: Programming Language :: Python :: 3
Classifier: Programming Language :: Python :: 3.9
Classifier: Programming Language :: Python :: 3.10
Classifier: Programming Language :: Python :: 3.11
Classifier: Programming Language :: Python :: 3.12
Classifier: Topic :: Utilities
Requires-Dist: Pillow
Requires-Dist: annofabapi (>=1.4.1,<2.0.0)
Requires-Dist: bokeh (>=3.3,<3.7)
Requires-Dist: dictdiffer
Requires-Dist: isodate
Requires-Dist: more-itertools
Requires-Dist: numpy
Requires-Dist: pandas (>=2,<3)
Requires-Dist: pyquery
Requires-Dist: python-datauri
Requires-Dist: pyyaml
Requires-Dist: requests
Requires-Dist: typing-extensions (>=4.5,<5.0)
Project-URL: Repository, https://github.com/kurusugawa-computer/annofab-cli
